aws_codedeploy_watcher/__init__.py
aws_codedeploy_watcher/deploy.py
aws_codedeploy_watcher/logs.py
aws_codedeploy_watcher-0.1.7.dist-info/entry_points.txt
aws_codedeploy_watcher-0.1.7.dist-info/LICENSE
aws_codedeploy_watcher-0.1.7.dist-info/WHEEL
aws_codedeploy_watcher-0.1.7.dist-info/METADATA
aws_codedeploy_watcher-0.1.7.dist-info/RECORD
