Metadata-Version: 2.1
Name: aws-codedeploy-watcher
Version: 0.1.7
Summary: Observe AWS Codedeploy deployments live
Home-page: UNKNOWN
License: MIT
Author: Daniel Miranda
Author-email: danielkza2@gmail.com
Requires-Python: >=2.7, !=3.0.*, !=3.1.*, !=3.2.*, !=3.3.*
Classifier: License :: OSI Approved :: MIT License
Classifier: Programming Language :: Python :: 2
Classifier: Programming Language :: Python :: 2.7
Classifier: Programming Language :: Python :: 3
Classifier: Programming Language :: Python :: 3.4
Classifier: Programming Language :: Python :: 3.5
Classifier: Programming Language :: Python :: 3.6
Classifier: Programming Language :: Python :: 3.7
Requires-Dist: boto3 (>=1.9,<2.0)
Requires-Dist: botocore (>=1.12,<2.0)
Requires-Dist: pendulum (>=2.0,<3.0)
